{
	"factoryName"	: "リヨン石油加工場",

	"recipeList" : [
		{
			"recipeName" : "ゴム",
			"recipeNum" : 6
		},
		{
			"recipeName" : "プラスチック",
			"recipeNum" : 6
		},
		{
			"recipeName" : "石油コークス",
			"recipeNum" : 5
		}
	],

	"inputlLineList" : [
		"鉄道駅_原油"
	],

	"outputLineList" :[
		"鉄道駅_ゴム",
		"鉄道駅_プラスチック",
		"AWESOMEシンク"
	],

	"relationships"	: [
		{
			"supplierLine" : "鉄道駅_原油",
			"destinationLine" : "ゴム製造ライン",
			"supplyItem" : "原油",
			"supplyNum" : 180
		},
		
		{
			"supplierLine" : "鉄道駅_原油",
			"destinationLine" : "プラスチック製造ライン",
			"supplyItem" : "原油",
			"supplyNum" : 180
		},

		{
			"supplierLine" : "ゴム製造ライン",
			"destinationLine" : "鉄道駅_ゴム",
			"supplyItem" : "ゴム",
			"supplyNum" : 120
		},
		{
			"supplierLine" : "ゴム製造ライン",
			"destinationLine" : "石油コークス製造ライン",
			"supplyItem" : "廃重油",
			"supplyNum" : 120
		},

		{
			"supplierLine" : "プラスチック製造ライン",
			"destinationLine" : "鉄道駅_プラスチック",
			"supplyItem" : "プラスチック",
			"supplyNum" : 120
		},
		{
			"supplierLine" : "プラスチック製造ライン",
			"destinationLine" : "石油コークス製造ライン",
			"supplyItem" : "廃重油",
			"supplyNum" : 60
		},
		{
			"supplierLine" : "石油コークス製造ライン",
			"destinationLine" : "AWESOMEシンク",
			"supplyItem" : "石油コークス",
			"supplyNum" : 720
		}

	]
}